pygraft/__init__.py
pygraft/cli.py
pygraft/paths.py
pygraft/py.typed
pygraft/pygraft.py
pygraft/types.py
pygraft/cli/__init__.py
pygraft/cli/extract_helper.py
pygraft/cli/formatting.py
pygraft/cli/main.py
pygraft/cli/validators.py
pygraft/cli/commands/__init__.py
pygraft/cli/commands/build.py
pygraft/cli/commands/explain.py
pygraft/cli/commands/extract.py
pygraft/cli/commands/init.py
pygraft/cli/commands/kg.py
pygraft/cli/commands/schema.py
pygraft/generators/__init__.py
pygraft/generators/classes.py
pygraft/generators/relations.py
pygraft/generators/schema.py
pygraft/generators/kg/__init__.py
pygraft/generators/kg/config.py
pygraft/generators/kg/entities.py
pygraft/generators/kg/generation.py
pygraft/generators/kg/kg.py
pygraft/generators/kg/output.py
pygraft/generators/kg/schema.py
pygraft/generators/kg/structures.py
pygraft/generators/kg/types.py
pygraft/ontology_extraction/__init__.py
pygraft/ontology_extraction/classes.py
pygraft/ontology_extraction/extraction.py
pygraft/ontology_extraction/namespaces.py
pygraft/ontology_extraction/queries.py
pygraft/ontology_extraction/relations.py
pygraft/resources/property_checks/combinations.json
pygraft/resources/property_checks/compat_p1p2_inverseof.txt
pygraft/resources/queries/ontology/classes/class2disjoints.rq
pygraft/resources/queries/ontology/classes/class2disjoints_extended.rq
pygraft/resources/queries/ontology/classes/classes.rq
pygraft/resources/queries/ontology/classes/direct_class2subclasses.rq
pygraft/resources/queries/ontology/classes/transitive_class2subclasses.rq
pygraft/resources/queries/ontology/relations/inverseof_relations.rq
pygraft/resources/queries/ontology/relations/rel2disjoints.rq
pygraft/resources/queries/ontology/relations/rel2disjoints_extended.rq
pygraft/resources/queries/ontology/relations/rel2dom_rel2range.rq
pygraft/resources/queries/ontology/relations/rel2patterns.rq
pygraft/resources/queries/ontology/relations/relations.rq
pygraft/resources/queries/ontology/relations/relations_seed.rq
pygraft_gen-0.0.11.dist-info/METADATA
pygraft_gen-0.0.11.dist-info/WHEEL
pygraft_gen-0.0.11.dist-info/entry_points.txt
pygraft_gen-0.0.11.dist-info/licenses/LICENSE.txt
pygraft_gen-0.0.11.dist-info/RECORD
