Metadata-Version: 2.4
Name: pygraft-gen
Version: 0.0.11
Summary: PyGraft-gen: Configurable generation of Schemas & Knowledge Graphs
Project-URL: Homepage, https://github.com/Orange-OpenSource/pygraft-gen
Project-URL: Repository, https://github.com/Orange-OpenSource/pygraft-gen.git
Project-URL: Issues, https://github.com/Orange-OpenSource/pygraft-gen/issues
Author-email: Lionel Tailhardat <lionel.tailhardat@orange.com>, Ovidiu Pascal <ovidiu.pascal@orange.com>, Nicolas Hubert <nicotab540@gmail.com>
Maintainer-email: Ovidiu Pascal <ovidiu.pascal@orange.com>, Lionel Tailhardat <lionel.tailhardat@orange.com>, Nicolas Hubert <nicotab540@gmail.com>
License: MIT License
License-File: LICENSE.txt
Keywords: Graph Generation,Knowledge Graph,Linked Data,OWL,Ontology,Ontology Extraction,RDF,RDFS,Schema,Semantic Web,Synthetic Data Generator
Classifier: Development Status :: 4 - Beta
Classifier: Intended Audience :: Science/Research
Classifier: License :: OSI Approved :: MIT License
Classifier: Programming Language :: Python :: 3 :: Only
Classifier: Programming Language :: Python :: 3.10
Classifier: Programming Language :: Python :: 3.11
Classifier: Programming Language :: Python :: 3.12
Classifier: Programming Language :: Python :: 3.13
Classifier: Topic :: Scientific/Engineering :: Artificial Intelligence
Classifier: Topic :: Scientific/Engineering :: Information Analysis
Classifier: Typing :: Typed
Requires-Python: >=3.10
Requires-Dist: numpy>=1.24.0
Requires-Dist: owlready2>=0.41
Requires-Dist: psutil>=7.1.3
Requires-Dist: pyyaml
Requires-Dist: rdflib>=6.2.0
Requires-Dist: tqdm
Requires-Dist: typer>=0.20.0
Provides-Extra: dev
Requires-Dist: basedpyright>=1.34.0; extra == 'dev'
Requires-Dist: build>=1.4.0; extra == 'dev'
Requires-Dist: codespell; extra == 'dev'
Requires-Dist: prek>=0.2.19; extra == 'dev'
Requires-Dist: pyright; extra == 'dev'
Requires-Dist: pytest; extra == 'dev'
Requires-Dist: ruff; extra == 'dev'
Provides-Extra: docs
Requires-Dist: mkdocs-git-revision-date-localized-plugin>=1.5.0; extra == 'docs'
Requires-Dist: mkdocs-material[imaging]>=9.7.1; extra == 'docs'
Requires-Dist: mkdocs>=1.6.1; extra == 'docs'
Requires-Dist: mkdocstrings[python]>=1.0.0; extra == 'docs'
